[null,{"name":"WelcomeMessage","temp":"member","event-type":"6","actions":[{"channel":"4","varName":"","message":"Hello ${tempVars(\"member\")}! , Welcome to [U.R] Clan\n!!rules aaml aléhom talla , check them out :) \n","storage":"0","varName2":"","name":"Send Message"}],"_id":"BtaJj"},{"name":"LeaveMessage","temp":"member","event-type":"7","actions":[{"channel":"4","varName":"","message":"${tempVars(\"member\")} Left the [U.R]\nNikni ken rja3","storage":"0","varName2":"","name":"Send Message"}],"_id":"haMMA"},{"name":"AutoResponse","temp":"msg","event-type":"0","actions":[{"message":"1","varName":"msg","info":"2","storage":"1","varName2":"text","name":"Store Message Info"},{"storage":"1","varName":"text","comparison":"6","value":"(nayek|zebi|9ahba)","iftrue":"0","iftrueVal":"","iffalse":"1","iffalseVal":"","name":"Check Variable"},{"message":"1","varName":"msg","info":"4","storage":"1","varName2":"channel","name":"Store Message Info"},{"channel":"5","varName":"channel","message":"Yezi bla sabén !","storage":"0","varName2":"","name":"Send Message"}],"_id":"WKYXz"}]